
     [
        {
          "category" : "Food",  
          "id": 1,
            "image":"./Resources/food3.jpg"       ,
            "title": "Canned Vegetables"
          },
          {
            "category" : "Food",
            "id": 2,
            "image":"./Resources/food1.jpg" ,
              "title": "Rice and Grains"
          },
          {
            "category" : "Food",
            "id": 3,
            "image":"/Resources/food2.jpg"  ,
            "title": "Canned Soup"
          },

          {
            "category" : "Health",
            "id": 4,
            "image": "/Resources/h3.jpg"     ,    
              "title": "First Aid Kit"
          },
          {
            "category" : "Health",
            "id": 5,
            "image": "/Resources/h1.jpg" ,
              "title": "Medical Supplies"
          },
          {
            "category" : "Health",
            "id": 6,
            "image": "/Resources/h2.jpg"     ,
            "title": "Personal Protective"
          },

          {
            "category" : "clothes",
            "id": 7,
            "image": "/Resources/c3.jpg",
            "title": "Winter Coats"
          },
          {
            "category" : "clothes",
            "id": 8,
            "image": "/Resources/c2.jpg",
            "title": "Children's Clothing"
          },
          {
            "category" : "clothes",
            "id": 9,
            "image": "/Resources/c1.jpg",
            "title": "Blankets welfare"
          },


          {
            "category" : "Education",
            "id": 10,
            "image": "/Resources/edu4.jpg",
            "title": "Laptops and Tablets"
          },
          {
            "category" : "Education",
            "id": 11,
            "image": "/Resources/edu3.jpg",
            "title": "Educational Books"
          },
          {
            "category" : "Education",
            "id": 12,
            "image": "/Resources/edu2.jpg",
            "title": "Scholarship Fund"
          }
       
      
      
      
      
      
     
    ]
  
  